woodstove/__init__.py
woodstove/acl.py
woodstove/app.py
woodstove/arguments.py
woodstove/boolean.py
woodstove/conf.py
woodstove/context.py
woodstove/db.py
woodstove/exceptions.py
woodstove/exhandler.py
woodstove/hooks.py
woodstove/log.py
woodstove/plugin.py
woodstove/request.py
woodstove/route.py
woodstove/server.py
woodstove/mgt/__init__.py
woodstove/mgt/debug.py
woodstove/mgt/root.py
woodstove/mgt/swagger.py
woodstove/plugins/__init__.py
woodstove/plugins/cors.py
woodstove/plugins/db.py
woodstove/plugins/duration.py
woodstove/plugins/trace.py
woodstove-0.1.1.dist-info/top_level.txt
woodstove-0.1.1.dist-info/METADATA
woodstove-0.1.1.dist-info/DESCRIPTION.rst
woodstove-0.1.1.dist-info/metadata.json
woodstove-0.1.1.dist-info/WHEEL
woodstove-0.1.1.dist-info/RECORD
