Metadata-Version: 2.0
Name: woodstove
Version: 0.1.1
Summary: A framework for writing HTTP service APIs
Home-page: https://github.com/richardmarshall/woodstove
Author: Richard Marshall
Author-email: richard.marshall@iacpub.com
License: UNKNOWN
Platform: UNKNOWN
Classifier: Development Status :: 4 - Beta
Classifier: Intended Audience :: Developers
Classifier: License :: OSI Approved :: Apache Software License
Classifier: Programming Language :: Python :: 2.7
Classifier: Programming Language :: Python :: 3
Classifier: Programming Language :: Python :: 3.2
Classifier: Programming Language :: Python :: 3.3
Classifier: Programming Language :: Python :: 3.4
Classifier: Programming Language :: Python :: 3.5
Classifier: Topic :: Internet :: WWW/HTTP :: Dynamic Content :: CGI Tools/Libraries
Classifier: Topic :: Internet :: WWW/HTTP :: WSGI
Classifier: Topic :: Internet :: WWW/HTTP :: WSGI :: Application
Classifier: Topic :: Internet :: WWW/HTTP :: WSGI :: Server
Classifier: Topic :: Software Development :: Libraries :: Application Frameworks
Requires: bottle
Requires: six
Requires-Dist: bottle
Requires-Dist: six
Provides-Extra: db
Requires-Dist: peewee; extra == 'db'
